oip_tracking_client/__init__.py
oip_tracking_client/api.py
oip_tracking_client/lib.py
oip_tracking_client/oip_header_plugin.py
oip_tracking_client/rest.py
oip_tracking_client/tracking.py
oip_tracking_client/utilies.py
oip_tracking_client/wavfile.py
oip_tracking_client/enums/__init__.py
oip_tracking_client/enums/metrics.py
oip_tracking_client/monitors/__init__.py
oip_tracking_client/monitors/amd_monitor.py
oip_tracking_client-0.0.18.dist-info/METADATA
oip_tracking_client-0.0.18.dist-info/WHEEL
oip_tracking_client-0.0.18.dist-info/entry_points.txt
oip_tracking_client-0.0.18.dist-info/top_level.txt
oip_tracking_client-0.0.18.dist-info/RECORD
