Metadata-Version: 2.1
Name: oip-tracking-client
Version: 0.0.18
Summary: This is the API client of Open Innovation Platform - Tracking
Author: Rachid Belmeskine
Author-email: rachid.belmeskine@gmail.com
License: PRIVATE LICENSE
Requires-Python: >=3.7
Requires-Dist: mlflow==2.16.2
Requires-Dist: deprecated
Requires-Dist: requests
Requires-Dist: pandas
Requires-Dist: typing
Requires-Dist: numpy
Requires-Dist: Pillow
Requires-Dist: matplotlib
Requires-Dist: plotly
Requires-Dist: psutil
Provides-Extra: amd
Requires-Dist: pyamdgpuinfo; extra == "amd"
Provides-Extra: nvidia
Requires-Dist: pynvml; extra == "nvidia"
